Metadata-Version: 2.1
Name: h99ex
Version: 0.1
Summary: Examples by h99hood
Author-email: keneskay@vk.com
